zaber_device/__init__.py
zaber_device/zaber_device.py
zaber_device-2.1.1.dist-info/LICENSE
zaber_device-2.1.1.dist-info/METADATA
zaber_device-2.1.1.dist-info/WHEEL
zaber_device-2.1.1.dist-info/top_level.txt
zaber_device-2.1.1.dist-info/RECORD
