Metadata-Version: 2.1
Name: zaber-device
Version: 2.1.1
Summary: Interface to Zaber motorized linear slides.
Home-page: https://github.com/janelia-pypi/zaber_device_python
Author: Peter Polidoro
Author-email: peterpolidoro@gmail.com
License: BSD
Keywords: zaber serial device
Platform: UNKNOWN
Classifier: Development Status :: 4 - Beta
Classifier: Intended Audience :: Developers
Classifier: Topic :: Software Development :: Build Tools
Classifier: License :: OSI Approved :: BSD License
Classifier: Programming Language :: Python :: 3
Requires-Dist: serial-interface
